<?xml version="1.0" encoding="utf-8" ?><dwsync><file name="avatar_delete.html" server="cybersurf.tk" local="3402094237" remote="12013549772" /><file name="avatar_edit.html" server="cybersurf.tk" local="3310284283" remote="12013549772" /><file name="avatar_list.html" server="cybersurf.tk" local="3402094237" remote="12013549772" /><file name="avatar_list_confirm.html" server="cybersurf.tk" local="3402094237" remote="12013549772" /><file name="avatar_upload.html" server="cybersurf.tk" local="3402094237" remote="12013549772" /><file name="avatar_upload_error.html" server="cybersurf.tk" local="3402094237" remote="12013549772" /><file name="group_delete.html" server="cybersurf.tk" local="3402094237" remote="12013549772" /><file name="group_edit.html" server="cybersurf.tk" local="3310284283" remote="12013549772" /><file name="group_list.html" server="cybersurf.tk" local="3402094237" remote="12013549772" /><file name="group_member.html" server="cybersurf.tk" local="3402094237" remote="12013549772" /><file name="group_perm.html" server="cybersurf.tk" local="3402094237" remote="12013549772" /><file name="group_property.html" server="cybersurf.tk" local="3402094237" remote="12013549772" /><file name="index.html" server="cybersurf.tk" local="3310284283" remote="12013549772" /><file name="mailjob_delete.html" server="cybersurf.tk" local="3310284283" remote="12013549772" /><file name="mailjob_edit.html" server="cybersurf.tk" local="3310284283" remote="12013549772" /><file name="mailjob_link_list.html" server="cybersurf.tk" local="3402094237" remote="12013549772" /><file name="mailjob_list.html" server="cybersurf.tk" local="3402094237" remote="12013549772" /><file name="mailjob_send.html" server="cybersurf.tk" local="3310284283" remote="12013549772" /><file name="mailjob_view.html" server="cybersurf.tk" local="3310284283" remote="12013549772" /><file name="ranks_delete.html" server="cybersurf.tk" local="3310284283" remote="12013549772" /><file name="ranks_edit.html" server="cybersurf.tk" local="3310284283" remote="12013549772" /><file name="ranks_list.html" server="cybersurf.tk" local="3402094237" remote="12013549772" /><file name="ranks_list_confirm.html" server="cybersurf.tk" local="3402094237" remote="12013549772" /><file name="user_data_download.html" server="cybersurf.tk" local="3402094237" remote="12013549772" /><file name="user_data_upload.html" server="cybersurf.tk" local="3402094237" remote="12013549772" /><file name="user_data_upload_conf.html" server="cybersurf.tk" local="3402094237" remote="12013549772" /><file name="user_delete.html" server="cybersurf.tk" local="3310284283" remote="12013549832" /><file name="user_edit.html" server="cybersurf.tk" local="3402094237" remote="12013549832" /><file name="user_list.html" server="cybersurf.tk" local="3402094237" remote="12013549832" /><file name="user_list_confirm.html" server="cybersurf.tk" local="3402094237" remote="12013549832" /><file name="user_search.html" server="cybersurf.tk" local="3402094237" remote="12013549832" /><file name="user_search_list.html" server="cybersurf.tk" local="3402094237" remote="12013549832" /><file name="user_search_list_confirm.html" server="cybersurf.tk" local="3402094237" remote="12013549832" /><file name="user_view.html" server="cybersurf.tk" local="3408548288" remote="12013549832" /></dwsync>